lotify/__init__.py
lotify/__version__.py
lotify/cli.py
lotify/client.py
lotify-2.3.4.dist-info/LICENSE
lotify-2.3.4.dist-info/METADATA
lotify-2.3.4.dist-info/WHEEL
lotify-2.3.4.dist-info/entry_points.txt
lotify-2.3.4.dist-info/top_level.txt
lotify-2.3.4.dist-info/RECORD
