Metadata-Version: 2.1
Name: lotify
Version: 2.3.4
Summary: Using LINE Notify more easily
Home-page: https://github.com/louis70109/line-notify
Author: NiJia Lin
Author-email: louis70109@gmail.com
Maintainer: NiJia Lin
Maintainer-email: louis70109@gmail.com
License: MIT
Project-URL: Bug Reports, https://github.com/louis70109/lotify/issues
Project-URL: Source, https://github.com/louis70109/lotify
Keywords: LINE notify python lotify
Platform: UNKNOWN
Classifier: Development Status :: 5 - Production/Stable
Classifier: License :: OSI Approved :: MIT License
Classifier: Intended Audience :: Developers
Classifier: Programming Language :: Python
Classifier: Programming Language :: Python :: 3
Classifier: Programming Language :: Python :: 3.5
Classifier: Programming Language :: Python :: 3.6
Classifier: Programming Language :: Python :: 3.7
Classifier: Programming Language :: Python :: 3.8
Classifier: Topic :: Software Development
Requires-Python: !=3.0.*, !=3.1.*, !=3.2.*, !=3.3.*, !=3.4.*
Requires-Dist: requests (>=2.0)
